LICENSE
MANIFEST.in
README.md
setup.cfg
setup.py
django_korean_fields.egg-info/PKG-INFO
django_korean_fields.egg-info/SOURCES.txt
django_korean_fields.egg-info/dependency_links.txt
django_korean_fields.egg-info/top_level.txt
korean/__init__.py
korean/admin.py
korean/apps.py
korean/fields.py
korean/models.py
korean/tests.py
korean/widgets.py
korean/static/.DS_Store
korean/static/korean/.DS_Store
korean/static/korean/css/korean.css
korean/static/korean/js/bupin.js
korean/static/korean/js/cell.js
korean/static/korean/js/jumin.js
korean/static/korean/js/saup.js
korean/static/korean/js/synchronize_input.js
korean/templates/korean/widgets/jumin.html
korean/templates/korean/widgets/saup.html
korean/templates/korean/widgets/synced.html