Metadata-Version: 1.1
Name: django-korean-fields
Version: 0.2.0
Summary: Django field & widget for korean people registration code aka Jumin-bunho
Home-page: https://github.com/bluedisk/django-korean-fields
Author: Matthew, lee
Author-email: bluedisk@gmail.com
License: MIT
Keywords: django field widget korean registration jumin saup bupin
Platform: UNKNOWN
Classifier: Development Status :: 4 - Beta
Classifier: Intended Audience :: Developers
Classifier: License :: OSI Approved :: MIT License
Classifier: Framework :: Django
Classifier: Environment :: Web Environment
Classifier: Topic :: Internet :: WWW/HTTP
Classifier: Topic :: Internet :: WWW/HTTP :: Dynamic Content
Classifier: Programming Language :: Python :: 3.4
Classifier: Programming Language :: Python :: 3.5
Classifier: Programming Language :: Python :: 3.6
Classifier: Programming Language :: Python :: 3.7
Classifier: Programming Language :: Python :: Implementation :: PyPy
